streamlit_webix/__init__.py
streamlit_webix/frontend/index.html
streamlit_webix/frontend/main.js
streamlit_webix/frontend/streamlit-component-lib.js
streamlit_webix/frontend/style.css
streamlit_webix-0.3.1.dist-info/licenses/LICENSE
streamlit_webix-0.3.1.dist-info/METADATA
streamlit_webix-0.3.1.dist-info/WHEEL
streamlit_webix-0.3.1.dist-info/top_level.txt
streamlit_webix-0.3.1.dist-info/RECORD
