Metadata-Version: 2.4
Name: streamlit-webix
Version: 0.3.1
Summary: Streamlit wrapper for the Webix UI library
Author: Hans Then
Author-email: hans.then@gmail.com
Requires-Python: >=3.7
License-File: LICENSE
Requires-Dist: streamlit>=1.2
Requires-Dist: jinja2
Dynamic: author
Dynamic: author-email
Dynamic: description
Dynamic: description-content-type
Dynamic: license-file
Dynamic: requires-dist
Dynamic: requires-python
Dynamic: summary
